{
    "version": "0.2",
    "language": "en",
    "words": [
        "BTCUSDT",
        "ETHUSDT", 
        "BNBUSDT",
        "SOLUSDT",
        "XRPUSDT",
        "ADAUSDT",
        "DOGEUSDT",
        "AVAXUSDT",
        "TRXUSDT",
        "DOTUSDT",
        "lognormal",
        "lookback",
        "intraday",
        "OHLCV",
        "zscore",
        "backtest",
        "backtesting",
        "cryptocurrency",
        "crypto",
        "binance",
        "parquet",
        "dataframe",
        "timestamp",
        "timestamps",
        "monotonic",
        "winsorization",
        "microstructure",
        "volatility",
        "slippage",
        "drawdown",
        "sharpe",
        "atr",
        "rsi",
        "bollinger",
        "ema",
        "vwap",
        "pyarrow",
        "pytest",
        "jsonl",
        "pnl",
        "bps",
        "algo",
        "algorithmic",
        "dedupe",
        "deduplication",
        "normalization",
        "partitioned",
        "partitioning",
        "provenance",
        "enum",
        "dtype",
        "dtypes",
        "nullable",
        "fillna",
        "dropna",
        "iloc",
        "loc",
        "groupby",
        "cummax",
        "cumsum",
        "ewm",
        "quantile",
        "percentile",
        "isna",
        "notna",
        "isnull",
        "notnull",
        "timedelta",
        "isoformat",
        "strftime",
        "utcnow",
        "tzinfo",
        "timezone",
        "datetime",
        "nanoseconds",
        "milliseconds",
        "microseconds"
    ],
    "ignorePaths": [
        "**/.git/**",
        "**/node_modules/**",
        "**/.venv/**",
        "**/__pycache__/**",
        "**/logs/**",
        "**/data/**",
        "**/reports/**",
        "**/*.pyc",
        "**/.pytest_cache/**"
    ],
    "includeRegExpList": [
        "/.*\\.(py|md|yaml|yml|json|txt)$/"
    ]
}
